README.md
setup.py
wehd/__init__.py
wehd/blur.py
wehd/distance.py
wehd.egg-info/PKG-INFO
wehd.egg-info/SOURCES.txt
wehd.egg-info/dependency_links.txt
wehd.egg-info/requires.txt
wehd.egg-info/top_level.txt